izifizi/__init__.py
izifizi/module.py
izifizi/py.typed
izifizi-1.0.0b2.dist-info/METADATA
izifizi-1.0.0b2.dist-info/WHEEL
izifizi-1.0.0b2.dist-info/RECORD
