Metadata-Version: 2.4
Name: izifizi
Version: 1.0.0b2
Summary: Python package for physics lab experiments
Author-email: Gil-Ad Shay <giladshay123@gmail.com>, Yael Bacil <yaelbacil@gmail.com>
Requires-Python: >=3.12
